notionit/__init__.py
notionit/__main__.py
notionit/_utils.py
notionit/config.py
notionit/math_plugin.py
notionit/py.typed
notionit/renderer.py
notionit/types.py
notionit/uploader.py
notionit-0.1.3.dist-info/METADATA
notionit-0.1.3.dist-info/WHEEL
notionit-0.1.3.dist-info/entry_points.txt
notionit-0.1.3.dist-info/top_level.txt
notionit-0.1.3.dist-info/RECORD
