Metadata-Version: 2.4
Name: notionit
Version: 0.1.3
Summary: A Python package for Notion API: Markdown to Notion uploader with full-featured support powered by Mistune.
Requires-Python: >=3.10
Requires-Dist: mistune>=3.1.3
Requires-Dist: requests>=2.25.0
Requires-Dist: rich>=14.0.0
Requires-Dist: spargear>=0.2.2
Requires-Dist: typing-extensions>=4.0.0
Provides-Extra: dev
Requires-Dist: pyright>=1.1.345; extra == "dev"
Requires-Dist: ruff>=0.11.13; extra == "dev"
